openpanel/__init__.py
openpanel/openpanel.py
openpanel-0.0.1.dist-info/LICENSE.md
openpanel-0.0.1.dist-info/METADATA
openpanel-0.0.1.dist-info/WHEEL
openpanel-0.0.1.dist-info/top_level.txt
openpanel-0.0.1.dist-info/RECORD
