Metadata-Version: 2.1
Name: openpanel
Version: 0.0.1
Summary: OpenPanel SDK for Python
Home-page: https://github.com/Openpanel-dev/python-sdk
Author: OpenPanel
Author-email: hello@openpanel.dev
License: AGPL-3.0-or-later
Platform: UNKNOWN
Classifier: Programming Language :: Python :: 3
Classifier: License :: OSI Approved :: GNU Affero General Public License v3
Classifier: Operating System :: OS Independent
Requires-Python: >=3.7
Requires-Dist: requests (>=2.28.1)
